{
  "indexes": [
    {
      "collectionGroup": "deeds",
      "queryScope": "COLLECTION",
      "fields": [
        {
          "fieldPath": "notifiee",
          "arrayConfig": "CONTAINS"
        },
        {
          "fieldPath": "createdAt",
          "order": "ASCENDING"
        }
      ]
    },
    {
      "collectionGroup": "deeds",
      "queryScope": "COLLECTION",
      "fields": [
        {
          "fieldPath": "notifiee",
          "arrayConfig": "CONTAINS"
        },
        {
          "fieldPath": "createdAt",
          "order": "DESCENDING"
        }
      ]
    },
    {
      "collectionGroup": "logs",
      "queryScope": "COLLECTION_GROUP",
      "fields": [
        {
          "fieldPath": "ancestorIds",
          "order": "ASCENDING"
        },
        {
          "fieldPath": "startedAt",
          "order": "DESCENDING"
        }
      ]
    },
    {
      "collectionGroup": "messages",
      "queryScope": "COLLECTION",
      "fields": [
        {
          "fieldPath": "fromto",
          "order": "ASCENDING"
        },
        {
          "fieldPath": "createdAt",
          "order": "ASCENDING"
        }
      ]
    },
    {
      "collectionGroup": "messages",
      "queryScope": "COLLECTION",
      "fields": [
        {
          "fieldPath": "fromto",
          "order": "ASCENDING"
        },
        {
          "fieldPath": "createdAt",
          "order": "DESCENDING"
        }
      ]
    },
    {
      "collectionGroup": "tasks",
      "queryScope": "COLLECTION_GROUP",
      "fields": [
        {
          "fieldPath": "involved",
          "arrayConfig": "CONTAINS"
        },
        {
          "fieldPath": "typeStatus",
          "order": "ASCENDING"
        }
      ]
    },
    {
      "collectionGroup": "tasks",
      "queryScope": "COLLECTION",
      "fields": [
        {
          "fieldPath": "involved",
          "arrayConfig": "CONTAINS"
        },
        {
          "fieldPath": "ancestorIds",
          "order": "ASCENDING"
        }
      ]
    },
    {
      "collectionGroup": "tasks",
      "queryScope": "COLLECTION",
      "fields": [
        {
          "fieldPath": "involved",
          "arrayConfig": "CONTAINS"
        },
        {
          "fieldPath": "typeStatus",
          "order": "ASCENDING"
        }
      ]
    },
    {
      "collectionGroup": "templates",
      "queryScope": "COLLECTION",
      "fields": [
        {
          "fieldPath": "userIds",
          "arrayConfig": "CONTAINS"
        },
        {
          "fieldPath": "projectId",
          "order": "ASCENDING"
        }
      ]
    }
  ],
  "fieldOverrides": [
    {
      "collectionGroup": "tasks",
      "fieldPath": "typeStatus",
      "ttl": false,
      "indexes": [
        {
          "order": "ASCENDING",
          "queryScope": "COLLECTION"
        },
        {
          "order": "DESCENDING",
          "queryScope": "COLLECTION"
        },
        {
          "arrayConfig": "CONTAINS",
          "queryScope": "COLLECTION"
        },
        {
          "order": "ASCENDING",
          "queryScope": "COLLECTION_GROUP"
        }
      ]
    }
  ]
}
